Workbook

Sheet Spread
A1: Line item ($M) | B1: Statement | C1: FY2022 | D1: FY2023 | E1: FY2024 | F1: FY2025
A2: revenue | B2: IS | C2: 5856.7 | D2: 5003.3 | E2: 4135.5 | F2: 4701.3
A3: cogs | B3: IS | C3: 1911.8 | D3: 1706 | E3: 1179.5 | F3: 1296.2
A4: operating_income | B4: IS | C4: 407.7 | D4: -1538.8 | E4: 690 | F4: 11.1
A5: depreciation_amortization | B5: IS | C5: 232.5 | D5: 210.7 | E5: 163 | F5: 135.5
A6: impairments | B6: IS | C6: 0 | D6: 1191.2 | E6: 0 | F6: 1021.9
A7: interest_expense | B7: IS | C7: 171 | D7: 186.3 | E7: 171.2 | F7: 163.4
A8: pretax_income | B8: IS | C8: 261.5 | D8: -1709.1 | E8: 497 | F8: -102
A9: income_tax | B9: IS | C9: 58.5 | D9: -221.3 | E9: 102.6 | F9: 216.2
A10: net_income | B10: IS | C10: 203.5 | D10: -1489.3 | E10: 385.6 | F10: -322.4
A11: operating_lease_cost | B11: IS | C11: 46.2 | D11: 44.2 | E11: 35.4 | F11: 32.8
A12: cash | B12: BS | C12: 513.1 | D12: 545.4 | E12: 695 | F12: 776.6
A13: receivables | B13: BS | C13: 1132.4 | D13: 1029.3 | E13: 919.8 | F13: 1059.8
... A27: dividends | B27: CF | C27: 385.3 | D27: 388 | E27: 389.9 | F27: 392.5
A29: Period end | C29: 2022-12-25 | D29: 2023-12-31 | E29: 2024-12-29 | F29: 2025-12-28

Sheet Ratios
A1: Ratio | B1: Key | C1: FY2022 | D1: FY2023 | E1: FY2024 | F1: FY2025
A2: EBITDA | B2: ebitda | C2: =Spread!C4+Spread!C5+Spread!C6 -> 640.2 | D2: =Spread!D4+Spread!D5+Spread!D6 -> -136.9 | E2: =Spread!E4+Spread!E5+Spread!E6 -> 853 | F2: =Spread!F4+Spread!F5+Spread!F6 -> 1168.5
A3: Total debt | B3: total_debt | C3: =Spread!C18+Spread!C19+Spread!C20 -> 3966.8 | D3: =Spread!D18+Spread!D19+Spread!D20 -> 3465.8 | E3: =Spread!E18+Spread!E19+Spread!E20 -> 3380.8 | F3: =Spread!F18+Spread!F19+Spread!F20 -> 3264.9
A4: Net debt | B4: net_debt | C4: =Spread!C18+Spread!C19+Spread!C20-Spread!C12 -> 3453.7 | D4: =Spread!D18+Spread!D19+Spread!D20-Spread!D12 -> 2920.4 | E4: =Spread!E18+Spread!E19+Spread!E20-Spread!E12 -> 2685.8 | F4: =Spread!F18+Spread!F19+Spread!F20-Spread!F12 -> 2488.3
A5: EBITDA margin | B5: ebitda_margin | C5: =IF(Spread!C2=0,"n/m",C2/Spread!C2) -> 0.1093107 | D5: =IF(Spread!D2=0,"n/m",D2/Spread!D2) -> -0.027361941 | E5: =IF(Spread!E2=0,"n/m",E2/Spread!E2) -> 0.20626285 | F5: =IF(Spread!F2=0,"n/m",F2/Spread!F2) -> 0.24854827
A6: Debt / EBITDA (x) | B6: debt_to_ebitda | C6: =IF(C2<=0,"n/m",C3/C2) -> 6.1961887 | D6: =IF(D2<=0,"n/m",D3/D2) -> n/m | E6: =IF(E2<=0,"n/m",E3/E2) -> 3.9634232 | F6: =IF(F2<=0,"n/m",F3/F2) -> 2.794095
A7: Net debt / EBITDA (x) | B7: net_leverage | C7: =IF(C2<=0,"n/m",C4/C2) -> 5.3947204 | D7: =IF(D2<=0,"n/m",D4/D2) -> n/m | E7: =IF(E2<=0,"n/m",E4/E2) -> 3.1486518 | F7: =IF(F2<=0,"n/m",F4/F2) -> 2.1294822
A8: EBIT / interest (x) | B8: interest_coverage | C8: =IF(Spread!C7=0,"n/m",(Spread!C4+Spread!C6)/Spread!C7) -> 2.3842105 | D8: =IF(Spread!D7=0,"n/m",(Spread!D4+Spread!D6)/Spread!D7) -> -1.8658078 | E8: =IF(Spread!E7=0,"n/m",(Spread!E4+Spread!E6)/Spread!E7) -> 4.0303738 | F8: =IF(Spread!F7=0,"n/m",(Spread!F4+Spread!F6)/Spread!F7) -> 6.3219094
A9: DSCR (x) | B9: dscr | C9: =IF((Spread!C7+Spread!C19)=0,"n/m",C2/(Spread!C7+Spread!C19)) -> 2.252639 | D9: =IF((Spread!D7+Spread!D19)=0,"n/m",D2/(Spread!D7+Spread!D19)) -> -0.19947545 | E9: =IF((Spread!E7+Spread!E19)=0,"n/m",E2/(Spread!E7+Spread!E19)) -> 4.9824766 | F9: =IF((Spread!F7+Spread!F19)=0,"n/m",F2/(Spread!F7+Spread!F19)) -> 1.7693822
A10: Fixed-charge coverage (x) | B10: fccr | C10: =IF((Spread!C7+Spread!C11+Spread!C19)=0,"n/m",(C2+Spread!C11-Spread!C25-Spread!C26)/(Spread!C7+Spread!C11+Spread!C19)) -> 1.1531477 | D10: =IF((Spread!D7+Spread!D11+Spread!D19)=0,"n/m",(D2+Spread!D11-Spread!D25-Spread!D26)/(Spread!D7+Spread!D11+Spread!D19)) -> -0.47638604 | E10: =IF((Spread!E7+Spread!E11+Spread!E19)=0,"n/m",(E2+Spread!E11-Spread!E25-Spread!E26)/(Spread!E7+Spread!E11+Spread!E19)) -> 3.429332 | F10: =IF((Spread!F7+Spread!F11+Spread!F19)=0,"n/m",(F2+Spread!F11-Spread!F25-Spread!F26)/(Spread!F7+Spread!F11+Spread!F19)) -> 1.3577611
A11: Current ratio (x) | B11: current_ratio | C11: =IF(Spread!C17=0,"n/m",Spread!C15/Spread!C17) -> 1.3696397 | D11: =IF(Spread!D17=0,"n/m",Spread!D15/Spread!D17) -> 1.1299358 | E11: =IF(Spread!E17=0,"n/m",Spread!E15/Spread!E17) -> 1.6002997 | F11: =IF(Spread!F17=0,"n/m",Spread!F15/Spread!F17) -> 1.3808455
A12: Free cash flow | B12: free_cash_flow | C12: =Spread!C24-Spread!C25 -> 244.7 | D12: =Spread!D24-Spread!D25 -> 590.1 | E12: =Spread!E24-Spread!E25 -> 760.2 | F12: =Spread!F24-Spread!F25 -> 829.9
A13: Debt / equity (x) | B13: debt_to_equity | C13: =IF(Spread!C22<=0,"n/m",C3/Spread!C22) -> 1.3860722 | D13: =IF(Spread!D22<=0,"n/m",D3/Spread!D22) -> 3.1884085 | E13: =IF(Spread!E22<=0,"n/m",E3/Spread!E22) -> 2.8529958 | F13: =IF(Spread!F22<=0,"n/m",F3/Spread!F22) -> 5.7734748

Sheet Covenants
A1: Covenant | B1: Metric | C1: Test | D1: Threshold | E1: Actual FY2025 | F1: Headroom | G1: Status
A2: Max total leverage | B2: debt_to_ebitda | C2: <= | D2: 3.5 | E2: =Ratios!F6 -> 2.794095 | F2: =IF(ISNUMBER(E2),(D2-E2)/D2,"n/m") -> 0.20168714 | G2: =IF(ISNUMBER(F2),IF(F2>=0,"PASS","BREACH"),IF(C2="<=","BREACH","PASS")) -> PASS
A3: Min interest coverage | B3: interest_coverage | C3: >= | D3: 3 | E3: =Ratios!F8 -> 6.3219094 | F3: =IF(ISNUMBER(E3),(E3-D3)/D3,"n/m") -> 1.1073031 | G3: =IF(ISNUMBER(F3),IF(F3>=0,"PASS","BREACH"),IF(C3="<=","BREACH","PASS")) -> PASS
A4: Min fixed-charge coverage | B4: fccr | C4: >= | D4: 1.25 | E4: =Ratios!F10 -> 1.3577611 | F4: =IF(ISNUMBER(E4),(E4-D4)/D4,"n/m") -> 0.086208886 | G4: =IF(ISNUMBER(F4),IF(F4>=0,"PASS","BREACH"),IF(C4="<=","BREACH","PASS")) -> PASS
A5: Min current ratio | B5: current_ratio | C5: >= | D5: 1 | E5: =Ratios!F11 -> 1.3808455 | F5: =IF(ISNUMBER(E5),(E5-D5)/D5,"n/m") -> 0.38084549 | G5: =IF(ISNUMBER(F5),IF(F5>=0,"PASS","BREACH"),IF(C5="<=","BREACH","PASS")) -> PASS

Sheet Stress
A1: Scenario | B1: Covenant | C1: Breaking shock | D1: Result
A2: ebitda_shock | B2: Max total leverage | C2: 0.20168714 | D2: breaks at -20.2%
A3: ebitda_shock | B3: Min interest coverage | C3: 0.46452717 | D3: breaks at -46.5%
A4: ebitda_shock | B4: Min fixed-charge coverage | C4: 0.063928113 | D4: breaks at -6.4%
A5: ebitda_shock | B5: Min current ratio | D5: holds to -100.0%
A6: rate_shock | B6: Max total leverage | D6: holds to +2,000 bp
A7: rate_shock | B7: Min interest coverage | D7: holds to +2,000 bp
A8: rate_shock | B8: Min fixed-charge coverage | C8: 1830.3777 | D8: breaks at +1,830 bp
A9: rate_shock | B9: Min current ratio | D9: holds to +2,000 bp
A10: revenue_decline | B10: Max total leverage | C10: 0.069211309 | D10: breaks at -6.9%
A11: revenue_decline | B11: Min interest coverage | C11: 0.15940795 | D11: breaks at -15.9%
A12: revenue_decline | B12: Min fixed-charge coverage | C12: 0.021937682 | D12: breaks at -2.2%
A13: revenue_decline | B13: Min current ratio | D13: holds to -100.0%

Sheet Sources
A1: Line item | B1: FY2022 | C1: FY2023 | D1: FY2024 | E1: FY2025
A2: revenue | B2: RevenueFromContractWithCustomerExcludingAssessedTax | C2: RevenueFromContractWithCustomerExcludingAssessedTax | D2: RevenueFromContractWithCustomerExcludingAssessedTax | E2: RevenueFromContractWithCustomerExcludingAssessedTax
A3: cogs | B3: CostOfGoodsAndServicesSold | C3: CostOfGoodsAndServicesSold | D3: CostOfGoodsAndServicesSold | E3: CostOfGoodsAndServicesSold
A4: operating_income | B4: OperatingIncomeLoss | C4: OperatingIncomeLoss | D4: OperatingIncomeLoss | E4: OperatingIncomeLoss
A5: depreciation_amortization | B5: DepreciationDepletionAndAmortization | C5: DepreciationDepletionAndAmortization | D5: DepreciationDepletionAndAmortization | E5: DepreciationDepletionAndAmortization
A6: impairments | B6: GoodwillImpairmentLoss | C6: GoodwillImpairmentLoss | D6: GoodwillImpairmentLoss | E6: GoodwillImpairmentLoss
A7: interest_expense | B7: InterestExpense | C7: InterestExpense | D7: InterestExpenseNonoperating | E7: InterestExpenseNonoperating
A8: pretax_income | B8: IncomeLossFromContinuingOperationsBeforeIncomeTaxesExtraordinaryItemsNoncontrollingInterest | C8: IncomeLossFromContinuingOperationsBeforeIncomeTaxesExtraordinaryItemsNoncontrollingInterest | D8: IncomeLossFromContinuingOperationsBeforeIncomeTaxesExtraordinaryItemsNoncontrollingInterest | E8: IncomeLossFromContinuingOperationsBeforeIncomeTaxesExtraordinaryItemsNoncontrollingInterest
A9: income_tax | B9: IncomeTaxExpenseBenefit | C9: IncomeTaxExpenseBenefit | D9: IncomeTaxExpenseBenefit | E9: IncomeTaxExpenseBenefit
A10: net_income | B10: NetIncomeLoss | C10: NetIncomeLoss | D10: NetIncomeLoss | E10: NetIncomeLoss
A11: operating_lease_cost | B11: OperatingLeaseCost | C11: OperatingLeaseCost | D11: OperatingLeaseCost | E11: OperatingLeaseCost
A12: cash | B12: CashCashEquivalentsRestrictedCashAndRestrictedCashEquivalents | C12: CashCashEquivalentsRestrictedCashAndRestrictedCashEquivalents | D12: CashCashEquivalentsRestrictedCashAndRestrictedCashEquivalents | E12: CashCashEquivalentsRestrictedCashAndRestrictedCashEquivalents
... A27: dividends | B27: PaymentsOfDividends | C27: PaymentsOfDividends | D27: PaymentsOfDividends | E27: PaymentsOfDividends
