Workbook

Sheet Spread
A1: Line item ($M) | B1: Statement | C1: FY2022 | D1: FY2023 | E1: FY2024
A2: revenue | B2: IS | C2: 365 | D2: 398 | E2: 420
A3: cogs | B3: IS | C3: 259 | D3: 280 | E3: 294
A4: operating_income | B4: IS | C4: 33 | D4: 38 | E4: 42
A5: depreciation_amortization | B5: IS | C5: 10 | D5: 11 | E5: 12
A6: impairments | B6: IS | C6: 0 | D6: 0 | E6: 0
A7: interest_expense | B7: IS | C7: 8 | D7: 10 | E7: 11
A8: pretax_income | B8: IS | C8: 25 | D8: 28 | E8: 31
A9: income_tax | B9: IS | C9: 6 | D9: 6 | E9: 7
A10: net_income | B10: IS | C10: 19 | D10: 22 | E10: 24
A11: operating_lease_cost | B11: IS | C11: 5 | D11: 6 | E11: 6
A12: cash | B12: BS | C12: 12 | D12: 14 | E12: 15
A13: receivables | B13: BS | C13: 52 | D13: 57 | E13: 60
... A27: dividends | B27: CF | C27: 4 | D27: 4 | E27: 5
A29: Period end | C29: 2022-12-31 | D29: 2023-12-31 | E29: 2024-12-31

Sheet Ratios
A1: Ratio | B1: Key | C1: FY2022 | D1: FY2023 | E1: FY2024
A2: EBITDA | B2: ebitda | C2: =Spread!C4+Spread!C5+Spread!C6 -> 43 | D2: =Spread!D4+Spread!D5+Spread!D6 -> 49 | E2: =Spread!E4+Spread!E5+Spread!E6 -> 54
A3: Total debt | B3: total_debt | C3: =Spread!C18+Spread!C19+Spread!C20 -> 153 | D3: =Spread!D18+Spread!D19+Spread!D20 -> 160 | E3: =Spread!E18+Spread!E19+Spread!E20 -> 162
A4: Net debt | B4: net_debt | C4: =Spread!C18+Spread!C19+Spread!C20-Spread!C12 -> 141 | D4: =Spread!D18+Spread!D19+Spread!D20-Spread!D12 -> 146 | E4: =Spread!E18+Spread!E19+Spread!E20-Spread!E12 -> 147
A5: EBITDA margin | B5: ebitda_margin | C5: =IF(Spread!C2=0,"n/m",C2/Spread!C2) -> 0.11780822 | D5: =IF(Spread!D2=0,"n/m",D2/Spread!D2) -> 0.12311558 | E5: =IF(Spread!E2=0,"n/m",E2/Spread!E2) -> 0.12857143
A6: Debt / EBITDA (x) | B6: debt_to_ebitda | C6: =IF(C2<=0,"n/m",C3/C2) -> 3.5581395 | D6: =IF(D2<=0,"n/m",D3/D2) -> 3.2653061 | E6: =IF(E2<=0,"n/m",E3/E2) -> 3
A7: Net debt / EBITDA (x) | B7: net_leverage | C7: =IF(C2<=0,"n/m",C4/C2) -> 3.2790698 | D7: =IF(D2<=0,"n/m",D4/D2) -> 2.9795918 | E7: =IF(E2<=0,"n/m",E4/E2) -> 2.7222222
A8: EBIT / interest (x) | B8: interest_coverage | C8: =IF(Spread!C7=0,"n/m",(Spread!C4+Spread!C6)/Spread!C7) -> 4.125 | D8: =IF(Spread!D7=0,"n/m",(Spread!D4+Spread!D6)/Spread!D7) -> 3.8 | E8: =IF(Spread!E7=0,"n/m",(Spread!E4+Spread!E6)/Spread!E7) -> 3.8181818
A9: DSCR (x) | B9: dscr | C9: =IF((Spread!C7+Spread!C19)=0,"n/m",C2/(Spread!C7+Spread!C19)) -> 2.3888889 | D9: =IF((Spread!D7+Spread!D19)=0,"n/m",D2/(Spread!D7+Spread!D19)) -> 2.3333333 | E9: =IF((Spread!E7+Spread!E19)=0,"n/m",E2/(Spread!E7+Spread!E19)) -> 2.3478261
A10: Fixed-charge coverage (x) | B10: fccr | C10: =IF((Spread!C7+Spread!C11+Spread!C19)=0,"n/m",(C2+Spread!C11-Spread!C25-Spread!C26)/(Spread!C7+Spread!C11+Spread!C19)) -> 1.3478261 | D10: =IF((Spread!D7+Spread!D11+Spread!D19)=0,"n/m",(D2+Spread!D11-Spread!D25-Spread!D26)/(Spread!D7+Spread!D11+Spread!D19)) -> 1.3333333 | E10: =IF((Spread!E7+Spread!E11+Spread!E19)=0,"n/m",(E2+Spread!E11-Spread!E25-Spread!E26)/(Spread!E7+Spread!E11+Spread!E19)) -> 1.3793103
A11: Current ratio (x) | B11: current_ratio | C11: =IF(Spread!C17=0,"n/m",Spread!C15/Spread!C17) -> 1.4772727 | D11: =IF(Spread!D17=0,"n/m",Spread!D15/Spread!D17) -> 1.4947368 | E11: =IF(Spread!E17=0,"n/m",Spread!E15/Spread!E17) -> 1.5
A12: Free cash flow | B12: free_cash_flow | C12: =Spread!C24-Spread!C25 -> 17 | D12: =Spread!D24-Spread!D25 -> 20 | E12: =Spread!E24-Spread!E25 -> 24
A13: Debt / equity (x) | B13: debt_to_equity | C13: =IF(Spread!C22<=0,"n/m",C3/Spread!C22) -> 1.3909091 | D13: =IF(Spread!D22<=0,"n/m",D3/Spread!D22) -> 1.322314 | E13: =IF(Spread!E22<=0,"n/m",E3/Spread!E22) -> 1.2461538

Sheet Covenants
A1: Covenant | B1: Metric | C1: Test | D1: Threshold | E1: Actual FY2024 | F1: Headroom | G1: Status
A2: Max total leverage | B2: debt_to_ebitda | C2: <= | D2: 3.5 | E2: =Ratios!E6 -> 3 | F2: =IF(ISNUMBER(E2),(D2-E2)/D2,"n/m") -> 0.14285714 | G2: =IF(ISNUMBER(F2),IF(F2>=0,"PASS","BREACH"),IF(C2="<=","BREACH","PASS")) -> PASS
A3: Min interest coverage | B3: interest_coverage | C3: >= | D3: 3 | E3: =Ratios!E8 -> 3.8181818 | F3: =IF(ISNUMBER(E3),(E3-D3)/D3,"n/m") -> 0.27272727 | G3: =IF(ISNUMBER(F3),IF(F3>=0,"PASS","BREACH"),IF(C3="<=","BREACH","PASS")) -> PASS
A4: Min fixed-charge coverage | B4: fccr | C4: >= | D4: 1.25 | E4: =Ratios!E10 -> 1.3793103 | F4: =IF(ISNUMBER(E4),(E4-D4)/D4,"n/m") -> 0.10344828 | G4: =IF(ISNUMBER(F4),IF(F4>=0,"PASS","BREACH"),IF(C4="<=","BREACH","PASS")) -> PASS
A5: Min current ratio | B5: current_ratio | C5: >= | D5: 1.2 | E5: =Ratios!E11 -> 1.5 | F5: =IF(ISNUMBER(E5),(E5-D5)/D5,"n/m") -> 0.25 | G5: =IF(ISNUMBER(F5),IF(F5>=0,"PASS","BREACH"),IF(C5="<=","BREACH","PASS")) -> PASS

Sheet Stress
A1: Scenario | B1: Covenant | C1: Breaking shock | D1: Result
A2: ebitda_shock | B2: Max total leverage | C2: 0.14285714 | D2: breaks at -14.3%
A3: ebitda_shock | B3: Min interest coverage | C3: 0.16666667 | D3: breaks at -16.7%
A4: ebitda_shock | B4: Min fixed-charge coverage | C4: 0.069444444 | D4: breaks at -6.9%
A5: ebitda_shock | B5: Min current ratio | D5: holds to -100.0%
A6: rate_shock | B6: Max total leverage | D6: holds to +2,000 bp
A7: rate_shock | B7: Min interest coverage | C7: 308.64198 | D7: breaks at +309 bp
A8: rate_shock | B8: Min fixed-charge coverage | C8: 308.64198 | D8: breaks at +309 bp
A9: rate_shock | B9: Min current ratio | D9: holds to +2,000 bp
A10: revenue_decline | B10: Max total leverage | C10: 0.06122449 | D10: breaks at -6.1%
A11: revenue_decline | B11: Min interest coverage | C11: 0.071428571 | D11: breaks at -7.1%
A12: revenue_decline | B12: Min fixed-charge coverage | C12: 0.029761905 | D12: breaks at -3.0%
A13: revenue_decline | B13: Min current ratio | D13: holds to -100.0%

Sheet Sources
A1: Line item | B1: FY2022 | C1: FY2023 | D1: FY2024
A2: revenue | B2: RevenueFromContractWithCustomerExcludingAssessedTax | C2: RevenueFromContractWithCustomerExcludingAssessedTax | D2: RevenueFromContractWithCustomerExcludingAssessedTax
A3: cogs | B3: CostOfGoodsAndServicesSold | C3: CostOfGoodsAndServicesSold | D3: CostOfGoodsAndServicesSold
A4: operating_income | B4: OperatingIncomeLoss | C4: OperatingIncomeLoss | D4: OperatingIncomeLoss
A5: depreciation_amortization | B5: DepreciationDepletionAndAmortization | C5: DepreciationDepletionAndAmortization | D5: DepreciationDepletionAndAmortization
A6: impairments | B6: not reported (0) | C6: not reported (0) | D6: not reported (0)
A7: interest_expense | B7: InterestExpense | C7: InterestExpense | D7: InterestExpense
A8: pretax_income | B8: IncomeLossFromContinuingOperationsBeforeIncomeTaxesExtraordinaryItemsNoncontrollingInterest | C8: IncomeLossFromContinuingOperationsBeforeIncomeTaxesExtraordinaryItemsNoncontrollingInterest | D8: IncomeLossFromContinuingOperationsBeforeIncomeTaxesExtraordinaryItemsNoncontrollingInterest
A9: income_tax | B9: IncomeTaxExpenseBenefit | C9: IncomeTaxExpenseBenefit | D9: IncomeTaxExpenseBenefit
A10: net_income | B10: NetIncomeLoss | C10: NetIncomeLoss | D10: NetIncomeLoss
A11: operating_lease_cost | B11: OperatingLeaseCost | C11: OperatingLeaseCost | D11: OperatingLeaseCost
A12: cash | B12: CashAndCashEquivalentsAtCarryingValue | C12: CashAndCashEquivalentsAtCarryingValue | D12: CashAndCashEquivalentsAtCarryingValue
... A27: dividends | B27: PaymentsOfDividends | C27: PaymentsOfDividends | D27: PaymentsOfDividends
